{
  "originalUrl": "http://www.velokiev.com/forum/viewtopic.php?f=1&t=144335",
  "activity": "cycling",
  "title": "Кружок через Канев (двухдневка)",
  "description": "Маршрут: Киев - Украинка - Ржищев - Канев - Переяслав-Хмельнецкий - Борисполь - Бровары - Киев\nhttp://maps.yandex.ua/-/CVr7nZJi\n\nЕсть идея проехать этот кружок, посмотреть Канев и завораживающие краевиды тех мест. \n\nЕдем с баулами, ночуем недалеко от Канева на берегу под звёздами в палатках. При желании можно будет покупаться. Готовим кушать на костре, отдыхаем, ведем интересные беседы.\n\nНа второй день через Переяслав-Хмельницкий доезжаем домой.\n\nВ день получится около 150км с большим набором высоты.\n\nБюджет - 100-200грн на еду и воду.\n\nБез употребления алкояда.\n\nУчастие по согласованию с организатором.",
  "extra": {
    "gathering": {
      "place": "Договорное (в зависимости от того кто от куда будет ехать буду подбирать по маршруту).",
      "lat": null,
      "lng": null,
      "date": "2014-07-08",
      "time": "09:00:00"
    },
    "start": {
      "date": "2014-07-08",
      "time": "10:00:00"
    },
    "finish": {
      "place": "Киев",
      "lat": null,
      "lng": null,
      "date": "2014-07-10",
      "time": "20:00:00"
    },
    "distance": 300,
    "speed": {
      "from": 20,
      "to": 25
    },
    "roadSurface": {
      "dirt": 1,
      "asphalt": 99
    },
    "checklist": [
      "запаска",
      "вело-свет",
      "одежду для ночевки",
      "спальник",
      "каремат",
      "палатка",
      "плавки",
      "фотоаппарат",
      "перекус",
      "воду",
      "деньги",
      "средство от комаров",
      "телефон"
    ]
  }
}